pydigitalenergy/__init__.py
pydigitalenergy/adapter.py
pydigitalenergy/basegroup.py
pydigitalenergy/digitalenergy.py
pydigitalenergy/exceptions.py
pydigitalenergy/models.py
pydigitalenergy/cloudapi/__init__.py
pydigitalenergy/cloudapi/actors.py
pydigitalenergy/cloudapi/endpoints.py
pydigitalenergy/cloudapi/models/__init__.py
pydigitalenergy/cloudapi/models/machine.py
pydigitalenergy/cloudbroker/__init__.py
pydigitalenergy/cloudbroker/actors.py
pydigitalenergy/cloudbroker/endpoints.py
pydigitalenergy/cloudbroker/models/__init__.py
pydigitalenergy/cloudbroker/models/cluster.py
pydigitalenergy/cloudbroker/models/compute.py
pydigitalenergy/cloudbroker/models/disk.py
pydigitalenergy/cloudbroker/models/extnet.py
pydigitalenergy/cloudbroker/models/grid.py
pydigitalenergy/cloudbroker/models/host.py
pydigitalenergy/cloudbroker/models/image.py
pydigitalenergy/cloudbroker/models/node.py
pydigitalenergy/cloudbroker/models/sep.py
pydigitalenergy/cloudbroker/models/stack.py
pydigitalenergy/cloudbroker/models/vm.py
pydigitalenergy/libcloud/__init__.py
pydigitalenergy/system/__init__.py
pydigitalenergy/system/actors.py
pydigitalenergy/system/endpoints.py
pydigitalenergy/system/models/__init__.py
pydigitalenergy/system/models/grid.py
tests/__init__.py
tests/test_cloudbroker_api.py
tests/test_rest_adapter.py
PyDigitalEnergy-0.0.4.dist-info/LICENSE.txt
PyDigitalEnergy-0.0.4.dist-info/METADATA
PyDigitalEnergy-0.0.4.dist-info/WHEEL
PyDigitalEnergy-0.0.4.dist-info/top_level.txt
PyDigitalEnergy-0.0.4.dist-info/RECORD
