Metadata-Version: 2.1
Name: PyDigitalEnergy
Version: 0.0.4
Summary: Python wrapper for Digital Energy API
Home-page: https://github.com/TonyNovoselov/PyDigitalEnergy
Author: Anthony Novoselov
Author-email: novoselov.anthony@gmail.com
Project-URL: Issue Tracker, https://github.com/TonyNovoselov/PyDigitalEnergy/issues
Keywords: digital energy api wrapper
Classifier: Intended Audience :: Developers
Classifier: Programming Language :: Python :: 3
Classifier: License :: OSI Approved :: Apache Software License
Classifier: Operating System :: OS Independent
Requires-Python: >=3.7
License-File: LICENSE.txt
Requires-Dist: requests
